porringer_pipx-0.1.1.dev3.dist-info/METADATA
porringer_pipx-0.1.1.dev3.dist-info/WHEEL
porringer_pipx-0.1.1.dev3.dist-info/entry_points.txt
porringer_pipx-0.1.1.dev3.dist-info/licenses/LICENSE.md
porringer_pipx/__init__.py
porringer_pipx/plugin.py
porringer_pipx/py.typed
porringer_pipx-0.1.1.dev3.dist-info/RECORD
